macrometa_source_bigquery/__init__.py
macrometa_source_bigquery/sample_data.py
macrometa_source_bigquery/sync_bigquery.py
macrometa_source_bigquery-1.0.0.dist-info/LICENSE
macrometa_source_bigquery-1.0.0.dist-info/METADATA
macrometa_source_bigquery-1.0.0.dist-info/WHEEL
macrometa_source_bigquery-1.0.0.dist-info/entry_points.txt
macrometa_source_bigquery-1.0.0.dist-info/top_level.txt
macrometa_source_bigquery-1.0.0.dist-info/RECORD
