Metadata-Version: 2.1
Name: macrometa-source-bigquery
Version: 1.0.0
Summary: Macrometa source bigquery connector for extracting data from BigQuery
Home-page: https://github.com/Macrometacorp/macrometa-source-bigquery
Author: Macrometa
Classifier: License :: OSI Approved :: Apache Software License
Classifier: Programming Language :: Python :: 3 :: Only
License-File: LICENSE
Requires-Dist: getschema (>=0.1.2)
Requires-Dist: google-cloud-bigquery (==3.2.0)
Requires-Dist: simplejson (==3.11.1)
Requires-Dist: setuptools (>=40.3.0)
Requires-Dist: pipelinewise-singer-python (==1.2.0)
Requires-Dist: c8connector (>=0.0.24)
Requires-Dist: prometheus-client (==0.16.0)
